xgcondb/__about__.py
xgcondb/__init__.py
xgcondb/_pyxgdb.cpython-36m-aarch64-linux-gnu.so
xgcondb/_pyxgdb.so
xgcondb_driver-0.1.0.dist-info/METADATA
xgcondb_driver-0.1.0.dist-info/WHEEL
xgcondb_driver-0.1.0.dist-info/licenses/LICENSE
xgcondb_driver-0.1.0.dist-info/RECORD
